Metadata-Version: 1.2
Name: sqla-psql-search
Version: 0.1.0
Summary: Utilities for SQLAlchemy PostgreSQL's natural search.
Home-page: https://github.com/bustawin/sqla-psql-search
Author: Xavier Bustamante Talavera
Author-email: xavier@bustawin.com
License: AGPLV3
Project-URL: Documentation, https://github.com/bustawin/sqla-psql-search
Project-URL: Code, https://github.com/bustawin/sqla-psql-search
Project-URL: Issue tracker, https://github.com/bustawin/poli-enum/issues
Platform: UNKNOWN
Classifier: Development Status :: 4 - Beta
Classifier: Intended Audience :: Developers
Classifier: License :: OSI Approved :: GNU Affero General Public License v3
Classifier: Operating System :: OS Independent
Classifier: Programming Language :: Python :: 3 :: Only
Classifier: Programming Language :: Python :: 3.6
Classifier: Programming Language :: Python :: 3.7
Classifier: Programming Language :: Python :: 3.8
Classifier: Topic :: Database
Classifier: Topic :: Software Development :: Libraries :: Python Modules
Requires-Python: >=3.6
